aimodelshare/__init__.py
aimodelshare/aimsonnx.py
aimodelshare/api.py
aimodelshare/aws.py
aimodelshare/aws_client.py
aimodelshare/base_image.py
aimodelshare/bucketpolicy.py
aimodelshare/containerisation.py
aimodelshare/containerization.py
aimodelshare/custom_eval_metrics.py
aimodelshare/deploy_custom_lambda.py
aimodelshare/exceptions.py
aimodelshare/generatemodelapi.py
aimodelshare/leaderboard.py
aimodelshare/model.py
aimodelshare/modeluser.py
aimodelshare/object_oriented.py
aimodelshare/postprocessormodules.py
aimodelshare/preprocessormodules.py
aimodelshare/readme.md
aimodelshare/reproducibility.py
aimodelshare/tools.py
aimodelshare/utils.py
aimodelshare/containerization_templates/Dockerfile.txt
aimodelshare/containerization_templates/Dockerfile_PySpark.txt
aimodelshare/containerization_templates/buildspec.txt
aimodelshare/containerization_templates/lambda_function.txt
aimodelshare/custom_approach/__init__.py
aimodelshare/custom_approach/lambda_function.py
aimodelshare/data_sharing/download_data.py
aimodelshare/data_sharing/share_data.py
aimodelshare/data_sharing/data_sharing_templates/Dockerfile.txt
aimodelshare/data_sharing/data_sharing_templates/__init__.py
aimodelshare/data_sharing/data_sharing_templates/buildspec.txt
aimodelshare/data_sharing/data_sharing_templates/codebuild_policies.txt
aimodelshare/data_sharing/data_sharing_templates/codebuild_trust_relationship.txt
aimodelshare/iam/codebuild_policy.txt
aimodelshare/iam/codebuild_trust_relationship.txt
aimodelshare/iam/lambda_policy.txt
aimodelshare/iam/lambda_trust_relationship.txt
aimodelshare/json_templates/__init__.py
aimodelshare/json_templates/api_json.txt
aimodelshare/json_templates/integration_response.txt
aimodelshare/json_templates/lambda_policy_1.txt
aimodelshare/json_templates/lambda_policy_2.txt
aimodelshare/json_templates/lambda_role_1.txt
aimodelshare/json_templates/lambda_role_2.txt
aimodelshare/json_templates/auth/policy.txt
aimodelshare/json_templates/auth/role.txt
aimodelshare_nightly-0.0.104.dist-info/LICENSE
aimodelshare_nightly-0.0.104.dist-info/METADATA
aimodelshare_nightly-0.0.104.dist-info/WHEEL
aimodelshare_nightly-0.0.104.dist-info/top_level.txt
aimodelshare_nightly-0.0.104.dist-info/RECORD
